LICENSE
MANIFEST.in
README.rst
requirements.txt
setup.cfg
setup.py
hbp_sphinx_theme/__init__.py
hbp_sphinx_theme/layout.html
hbp_sphinx_theme/theme.conf
hbp_sphinx_theme.egg-info/PKG-INFO
hbp_sphinx_theme.egg-info/SOURCES.txt
hbp_sphinx_theme.egg-info/dependency_links.txt
hbp_sphinx_theme.egg-info/not-zip-safe
hbp_sphinx_theme.egg-info/top_level.txt
hbp_sphinx_theme/static/hbpdoc.css
hbp_sphinx_theme/static/hbpdoc.js
hbp_sphinx_theme/static/hbpdoc.min.css
hbp_sphinx_theme/static/hbpdoc.min.js
hbp_sphinx_theme/static/bower_components/hbp-collaboratory-theme/dist/fonts/glyphicons-halflings-regular.eot
hbp_sphinx_theme/static/bower_components/hbp-collaboratory-theme/dist/fonts/glyphicons-halflings-regular.svg
hbp_sphinx_theme/static/bower_components/hbp-collaboratory-theme/dist/fonts/glyphicons-halflings-regular.ttf
hbp_sphinx_theme/static/bower_components/hbp-collaboratory-theme/dist/fonts/glyphicons-halflings-regular.woff
hbp_sphinx_theme/static/bower_components/material-design-iconic-font/dist/fonts/Material-Design-Iconic-Font.eot
hbp_sphinx_theme/static/bower_components/material-design-iconic-font/dist/fonts/Material-Design-Iconic-Font.svg
hbp_sphinx_theme/static/bower_components/material-design-iconic-font/dist/fonts/Material-Design-Iconic-Font.ttf
hbp_sphinx_theme/static/bower_components/material-design-iconic-font/dist/fonts/Material-Design-Iconic-Font.woff