Metadata-Version: 1.1
Name: hbp-sphinx-theme
Version: 0.3.4
Summary: Human Brain Project Sphinx Theme.
Home-page: https://github.com/HumanBrainProject/hbp-sphinx-theme/
Author: Olivier Amblet
Author-email: olivier.amblet@epfl.ch
License: MIT
Platform: UNKNOWN
Classifier: Development Status :: 3 - Alpha
Classifier: License :: OSI Approved :: BSD License
Classifier: Environment :: Console
Classifier: Environment :: Web Environment
Classifier: Intended Audience :: Developers
Classifier: Programming Language :: Python :: 2.6
Classifier: Programming Language :: Python :: 2.7
Classifier: Programming Language :: Python :: 3
Classifier: Operating System :: OS Independent
Classifier: Topic :: Documentation
Classifier: Topic :: Software Development :: Documentation
